
{
   "response_code":0,
   "results":[
      {
         "category":"PSPO 1",
         "type":"multiple",
         "difficulty":"easy",
         "question":"Which approach is best for Scrum Team in order to produce valuable Increments?",
         "correct_answer":"Each Scrum Team is accountable for developing functionality from beginning to end.",
         "incorrect_answers":[
            "Each Scrum Team works on an independent set of components.",
            "Each Scrum Team Member work only as an independent layer of the system.",
            "Each Developer works on the component where they feel that they can contribute."
         ]
      },
      {
         "category":"Entertainment: PSPO 1",
         "type":"multiple",
         "difficulty":"easy",
         "question":"When is the Sprint Backlog created?",
         "correct_answer":"During Sprint Planning.",
         "incorrect_answers":[
            "During the Sprint Retrospective.",
            "Prior to Sprint Planning.",
            "During refinement."
         ]
      },
      {
         "category":"PSPO 1",
         "type":"multiple",
         "difficulty":"easy",
         "question":"Why is it important that there is only one Product Owner per product?",
         "correct_answer":[
            "It helps avoid barriers to effective communication and rapid decision-making.",
            "Scrum Team always knows who determines the order of the Product.",
            "It is clear who is accountable for the ultimate value of the product."
            ]
         "incorrect_answers":[
            "The Scrum Master knows who acts as their backup while on vacation.",
            "It would confuse the stakeholders if they had to work with more than one person."
             ]
      },
      {
         "category":"PSPO 1",
         "type":"multiple",
         "difficulty":"easy",
         "question":"By what name is Carlos Estevez better known? ",
         "correct_answer":"Charlie Sheen",
         "incorrect_answers":[
            "Ricky Martin",
            "Bruno Mars",
            "Joaquin Phoenix"
         ]
      },
      {
         "category":"PSPO 1",
         "type":"multiple",
         "difficulty":"easy",
         "question":" True or False: The Product Owner makes sure the correct stakeholders are invited to the Sprint Retrospective. They might have important instruction for team improvements.",
         "correct_answer":"False",
         "incorrect_answers":[
            "True"
            
         ]
      },
      {
         "category":"PSPO 1",
         "type":"multiple",
         "difficulty":"easy",
         "question":"What might indicate to a Product Owner that she needs to work more with the Scrum Team?",
         "correct_answer":"Lewis Hamilton",
         "incorrect_answers":[
            "Nico Rosberg",
            "Sebastian Vettel",
            "Jenson Button"
         ]
      },
      {
         "category":"Entertainment: Video Games",
         "type":"multiple",
         "difficulty":"easy",
         "question":"How many flagship monsters appear in Monster Hunter Gernerations?",
         "correct_answer":"4",
         "incorrect_answers":[
            "1",
            "2",
            "3"
         ]
      },
      {
         "category":"Entertainment: Video Games",
         "type":"multiple",
         "difficulty":"easy",
         "question":"Which Animal Crossing game was for the Nintendo Wii?",
         "correct_answer":"Animal Crossing: City Folk",
         "incorrect_answers":[
            "Animal Crossing: New Leaf",
            "Animal Crossing: Wild World",
            "Animal Crossing: Population Growing!"
         ]
      },
      {
         "category":"Entertainment: Video Games",
         "type":"multiple",
         "difficulty":"easy",
         "question":"Which Kirby game first introduced Copy Abilities?",
         "correct_answer":"Kirby&#039;s Adventure",
         "incorrect_answers":[
            "Kirby Super Star",
            "Kirby&#039;s Dream Land 2",
            "Kirby&#039;s Dream Land"
         ]
      },
      {
         "category":"Entertainment: Music",
         "type":"multiple",
         "difficulty":"easy",
         "question":"When was Gangnam Style uploaded to YouTube?",
         "correct_answer":"2012",
         "incorrect_answers":[
            "2013",
            "2014",
            "2011"
         ]
      }
            ,
      {
         "category":"Entertainment: Music",
         "type":"multiple",
         "difficulty":"easy",
         "question":"When was Gangnam Style uploaded to YouTube?",
         "correct_answer":"2012",
         "incorrect_answers":[
            "2013",
            "2014",
            "2011"
         ]
      }
   ]
}
